tcm/__init__.py
tcm/decorator.py
tcm/metaclass.py
tcm-2.0.0.dist-info/LICENSE
tcm-2.0.0.dist-info/METADATA
tcm-2.0.0.dist-info/WHEEL
tcm-2.0.0.dist-info/top_level.txt
tcm-2.0.0.dist-info/zip-safe
tcm-2.0.0.dist-info/RECORD
